api/__init__.py
api/_base.py
api/dummy.py
api/paper.py
api/polygon.py
api/robinhood.py
api/yahoo.py
plugin/__init__.py
plugin/_base.py
plugin/dolt_options_plugin.py
storage/__init__.py
storage/base_logger.py
storage/base_storage.py
storage/csv_storage.py
storage/database_storage.py
storage/pickle_storage.py
trader/__init__.py
trader/tester.py
trader/trader.py
harvest_algo-0.1.3.dist-info/LICENSE
harvest_algo-0.1.3.dist-info/METADATA
harvest_algo-0.1.3.dist-info/WHEEL
harvest_algo-0.1.3.dist-info/top_level.txt
harvest_algo-0.1.3.dist-info/RECORD
