Metadata-Version: 2.1
Name: harvest-algo
Version: 0.1.3
Summary: Simple and intuitive python framework for algorithmic trading.
Home-page: https://github.com/tfukaza/harvest/
Author: Harvest Team
License: UNKNOWN
Platform: UNKNOWN
Classifier: Programming Language :: Python :: 3
Classifier: License :: OSI Approved :: MIT License
Classifier: Operating System :: OS Independent
Requires-Python: >=3.8
License-File: LICENSE
Requires-Dist: pandas
Requires-Dist: finta
Requires-Dist: pyyaml
Requires-Dist: tqdm
Requires-Dist: pytz
Requires-Dist: yfinance
Requires-Dist: SQLAlchemy
Provides-Extra: alpacamarket
Requires-Dist: alpaca-trade-api ; extra == 'alpacamarket'
Provides-Extra: robinhood
Requires-Dist: pyotp ; extra == 'robinhood'
Requires-Dist: robin-stocks ; extra == 'robinhood'
